<?xml version="1.0" encoding="UTF-8"?><soapenv:Envelope xmlns:soapenv="http://www.w3.org/2003/05/soap-envelope" xmlns:xsd="http://www.w3.org/2001/XMLSchema" xmlns:xsi="http://www.w3.org/2001/XMLSchema-instance"><soapenv:Body><nfeResultMsg xmlns="http://www.portalfiscal.inf.br/nfe/wsdl/NFeRetAutorizacao4"><retConsReciNFe versao="4.00" xmlns="http://www.portalfiscal.inf.br/nfe">
<tpAmb>2</tpAmb>
<verAplic>NFEPE_H_1.3.0</verAplic>
<nRec>261200000620387</nRec>
<cStat>104</cStat>
<xMotivo>Lote processado</xMotivo>
<cUF>26</cUF><dhRecbto>2020-12-22T19:39:21-03:00</dhRecbto>
 <protNFe versao="4.00"><infProt Id="NFe1"><tpAmb>2</tpAmb>
<verAplic>NFEPE_H_1.3.0</verAplic>
<chNFe>26201224494200000106550010000010341035851498</chNFe>
<dhRecbto>2020-12-22T19:39:21-03:00</dhRecbto><nProt>126200000457491</nProt>
<digVal>pcJMDQjgsXHyVtKFJL+Ce3I16Tg=</digVal><cStat>100</cStat>
<xMotivo>Autorizado o uso da NF-e</xMotivo>
</infProt></protNFe></retConsReciNFe></nfeResultMsg></soapenv:Body></soapenv:Envelope>